<?xml version="1.0" encoding="utf-8" ?>
<dwsync>
<file name="color-picker.js" server="ftp.djdukkacalliery.com.br//" local="130434732000000000" remote="130434732000000000" Dst="1" />
<file name="discography.js" server="ftp.djdukkacalliery.com.br//" local="130434732000000000" remote="130434732000000000" Dst="1" />
<file name="jquery-1.11.0.min.js" server="ftp.djdukkacalliery.com.br//" local="130434732000000000" remote="130434732000000000" Dst="1" />
<file name="jquery.form.js" server="ftp.djdukkacalliery.com.br//" local="130434732000000000" remote="130434732000000000" Dst="1" />
<file name="jquery.hoverdir.js" server="ftp.djdukkacalliery.com.br//" local="130434732000000000" remote="130434732000000000" Dst="1" />
<file name="jquery.isotope.min.js" server="ftp.djdukkacalliery.com.br//" local="130434732000000000" remote="130434732000000000" Dst="1" />
<file name="jquery.nav.js" server="ftp.djdukkacalliery.com.br//" local="130434732000000000" remote="130434732000000000" Dst="1" />
<file name="jquery.scrolly.js" server="ftp.djdukkacalliery.com.br//" local="130434732000000000" remote="130434732000000000" Dst="1" />
<file name="jquery.validate.js" server="ftp.djdukkacalliery.com.br//" local="130434732000000000" remote="130434732000000000" Dst="1" />
<file name="news.js" server="ftp.djdukkacalliery.com.br//" local="130434732000000000" remote="130434732000000000" Dst="1" />
<file name="plugins.js" server="ftp.djdukkacalliery.com.br//" local="130434732000000000" remote="130434732000000000" Dst="1" />
<file name="sonorama.js" server="ftp.djdukkacalliery.com.br//" local="130434732000000000" remote="130434732000000000" Dst="1" />
<file name="tweets.js" server="ftp.djdukkacalliery.com.br//" local="130434732000000000" remote="130434732000000000" Dst="1" />
</dwsync>